{"name": "North Carolina Battered Catfish", "url": "https://raw.github.com/sinker/tacofancy/master/base_layers/battered_catfish.md", "recipe": "Do it right and [stick your arm down a catfish hole in the muddy waters of a north carolina pond](http://www.youtube.com/watch?v=zc_huHb4PMc), take that sucker home at serve it up to your friends and family on some corn tortilas\n\n* 1 cup all-purpose flour\n* 1 cup cornmeal\n* 1 tablespoon baking powder\n* 1 tablespoon kosher salt\n* 1/2 teaspoon cayenne pepper\n* 1 (12-ounce) bottle amber beer\n* 4 (6-ounce) catfish fillets\n* 1 tablespoon salt\n* 1 tablespoon cracked black pepper\n* 2 tablespoons granulated garlic\n* 1 lemon, juiced\n\nPreheat a deep-fryer to 350 degrees Fahrenheit.\n\nIn a large bowl, add the flour, cornmeal, baking powder, salt and cayenne and whisk to combine. Whisk in the beer, being sure to remove any lumps.\n\nCut the catfish fillets in half lengthwise to make 2 strips. If desired, cut into bite-sized pieces. In a small bowl add the salt, pepper and granulated garlic. Season the fillets with the salt mixture.\n\nDip each strip in the beer batter and add to the fryer, a few at a time, moving them around so they don't stick. Fry until brown and crispy, about 3 to 4 minutes. Remove from the fryer to a serving platter. Repeat with the remaining fillets and season the fish with lemon juice. Cut them up into taco size portions and show your friends how amazing your catch tastes.\n", "slug": "north_carolina_battered_catfish", "uuid": "2f064102-64eb-11ea-820b-acde48001122"}